mkdocs_quizdown_plugin/__init__.py
mkdocs_quizdown_plugin/plugin.py
mkdocs_quizdown_plugin/assets/quizdown.js
mkdocs_quizdown_plugin/assets/quizdown_init.js
mkdocs_quizdown_plugin-2025.3.3.dist-info/LICENSE
mkdocs_quizdown_plugin-2025.3.3.dist-info/METADATA
mkdocs_quizdown_plugin-2025.3.3.dist-info/WHEEL
mkdocs_quizdown_plugin-2025.3.3.dist-info/entry_points.txt
mkdocs_quizdown_plugin-2025.3.3.dist-info/top_level.txt
mkdocs_quizdown_plugin-2025.3.3.dist-info/RECORD
