Metadata-Version: 2.2
Name: mkdocs-quizdown-plugin
Version: 2025.3.3
Summary: MkDocs plugin for quizdown-js
Author-email: Thomas Breitner <mail@thms.de>
License: The MIT License
Project-URL: Repository, https://github.com/tombreit/mkdocs-quizdown-plugin
Project-URL: Homepage, https://github.com/tombreit/mkdocs-quizdown-plugin
Project-URL: Documentation, https://github.com/tombreit/mkdocs-quizdown-plugin/blob/main/README.md
Project-URL: Issues, https://github.com/tombreit/mkdocs-quizdown-plugin/issues
Classifier: Framework :: MkDocs
Classifier: Topic :: Documentation
Classifier: License :: OSI Approved :: MIT License
Classifier: Programming Language :: Python :: 3
Classifier: Development Status :: 3 - Alpha
Requires-Python: >=3.9
License-File: LICENSE
Requires-Dist: mkdocs>=1.6
Provides-Extra: pypi
Requires-Dist: build; extra == "pypi"
Requires-Dist: twine; extra == "pypi"
